ray_graph/__init__.py
ray_graph/epoch.py
ray_graph/event.py
ray_graph/graph.py
ray_graph/py.typed
ray_graph-0.6.7.dist-info/METADATA
ray_graph-0.6.7.dist-info/WHEEL
ray_graph-0.6.7.dist-info/licenses/LICENSE
ray_graph-0.6.7.dist-info/RECORD
